vmtplanner/__about__.py
vmtplanner/__init__.py
vmtplanner/plans.py
vmtplanner/vmtplanner.py
vmtplanner/plans/__init__.py
vmtplanner/processors/__init__.py
vmtplanner/processors/headroom.py
vmtplanner/processors/headroom_mp.py
vmtplanner/processors/headroom_old.py
vmtplan-2.3.0.dist-info/LICENSE
vmtplan-2.3.0.dist-info/METADATA
vmtplan-2.3.0.dist-info/WHEEL
vmtplan-2.3.0.dist-info/top_level.txt
vmtplan-2.3.0.dist-info/RECORD
