Metadata-Version: 2.1
Name: vmtplan
Version: 2.3.0
Summary: Turbonomic Plan Engine
Home-page: https://github.com/turbonomic/vmt-plan
Author: R.A. Stern
Author-email: richard.stern@turbonomic.com
License: Apache 2.0
Platform: UNKNOWN
Classifier: Intended Audience :: Developers
Classifier: License :: OSI Approved :: Apache Software License
Classifier: Operating System :: OS Independent
Classifier: Programming Language :: Python :: 3
Classifier: Topic :: Software Development
Requires-Python: >=3.6
Requires-Dist: vmtconnect (<4,>=3.4.1)
Requires-Dist: umsg (>=1.0.2)
